mydocuments.py
mydocuments-0.1.6.dist-info/METADATA
mydocuments-0.1.6.dist-info/WHEEL
mydocuments-0.1.6.dist-info/entry_points.txt
mydocuments-0.1.6.dist-info/top_level.txt
mydocuments-0.1.6.dist-info/RECORD
