Metadata-Version: 2.4
Name: mydocuments
Version: 0.1.6
Summary: Displays the path to the user's documents directory.
License-Expression: GPL-3.0-or-later
Project-URL: Homepage, https://github.com/maciakl/mydocuments
Project-URL: Issues, https://github.com/maciakl/mydocuments/issues
Keywords: documents,path,user,directory,cli
Requires-Python: >=3.11
